{"id":{"0":"QYJ_Test_1","1":"QYJ_Test_2","2":"QYJ_Test_3","3":"QYJ_Test_4","4":"QYJ_Test_5","5":"QYJ_Test_6","6":"QYJ_Test_7","7":"QYJ_Test_8","8":"QYJ_Training_1","9":"QYJ_Training_2","10":"QYJ_Training_3","11":"QYJ_Training_4","12":"QYJ_Training_5","13":"ZYF_Test_1","14":"ZYF_Test_2","15":"ZYF_Test_3","16":"ZYF_Test_4","17":"ZYF_Test_5","18":"ZYF_Test_6","19":"ZYF_Test_7","20":"ZYF_Test_8","21":"ZYF_Training_1","22":"ZYF_Training_2","23":"ZYF_Training_3","24":"ZYF_Training_4","25":"ZYF_Training_5"},"rawpath":{"0":"rawdata\/QYJ\/MultiTest_1_raw_tsss.fif","1":"rawdata\/QYJ\/MultiTest_2_raw_tsss.fif","2":"rawdata\/QYJ\/MultiTest_3_raw_tsss.fif","3":"rawdata\/QYJ\/MultiTest_4_raw_tsss.fif","4":"rawdata\/QYJ\/MultiTest_5_raw_tsss.fif","5":"rawdata\/QYJ\/MultiTest_6_raw_tsss.fif","6":"rawdata\/QYJ\/MultiTest_7_raw_tsss.fif","7":"rawdata\/QYJ\/MultiTest_8_raw_tsss.fif","8":"rawdata\/QYJ\/MultiTraining_1_raw_tsss.fif","9":"rawdata\/QYJ\/MultiTraining_2_raw_tsss.fif","10":"rawdata\/QYJ\/MultiTraining_3_raw_tsss.fif","11":"rawdata\/QYJ\/MultiTraining_4_raw_tsss.fif","12":"rawdata\/QYJ\/MultiTraining_5_raw_tsss.fif","13":"rawdata\/ZYF\/MultiTest_1_raw_tsss.fif","14":"rawdata\/ZYF\/MultiTest_2_raw_tsss.fif","15":"rawdata\/ZYF\/MultiTest_3_raw_tsss.fif","16":"rawdata\/ZYF\/MultiTest_4_raw_tsss.fif","17":"rawdata\/ZYF\/MultiTest_5_raw_tsss.fif","18":"rawdata\/ZYF\/MultiTest_6_raw_tsss.fif","19":"rawdata\/ZYF\/MultiTest_7_raw_tsss.fif","20":"rawdata\/ZYF\/MultiTest_8_raw_tsss.fif","21":"rawdata\/ZYF\/MultiTraining_1_raw_tsss.fif","22":"rawdata\/ZYF\/MultiTraining_2_raw_tsss.fif","23":"rawdata\/ZYF\/MultiTraining_3_raw_tsss.fif","24":"rawdata\/ZYF\/MultiTraining_4_raw_tsss.fif","25":"rawdata\/ZYF\/MultiTraining_5_raw_tsss.fif"},"rawica":{"0":"raw_ica\/QYJ_Test_1-afterica-raw.fif","1":"raw_ica\/QYJ_Test_2-afterica-raw.fif","2":"raw_ica\/QYJ_Test_3-afterica-raw.fif","3":"raw_ica\/QYJ_Test_4-afterica-raw.fif","4":"raw_ica\/QYJ_Test_5-afterica-raw.fif","5":"raw_ica\/QYJ_Test_6-afterica-raw.fif","6":"raw_ica\/QYJ_Test_7-afterica-raw.fif","7":"raw_ica\/QYJ_Test_8-afterica-raw.fif","8":"raw_ica\/QYJ_Training_1-afterica-raw.fif","9":"raw_ica\/QYJ_Training_2-afterica-raw.fif","10":"raw_ica\/QYJ_Training_3-afterica-raw.fif","11":"raw_ica\/QYJ_Training_4-afterica-raw.fif","12":"raw_ica\/QYJ_Training_5-afterica-raw.fif","13":"raw_ica\/ZYF_Test_1-afterica-raw.fif","14":"raw_ica\/ZYF_Test_2-afterica-raw.fif","15":"raw_ica\/ZYF_Test_3-afterica-raw.fif","16":"raw_ica\/ZYF_Test_4-afterica-raw.fif","17":"raw_ica\/ZYF_Test_5-afterica-raw.fif","18":"raw_ica\/ZYF_Test_6-afterica-raw.fif","19":"raw_ica\/ZYF_Test_7-afterica-raw.fif","20":"raw_ica\/ZYF_Test_8-afterica-raw.fif","21":"raw_ica\/ZYF_Training_1-afterica-raw.fif","22":"raw_ica\/ZYF_Training_2-afterica-raw.fif","23":"raw_ica\/ZYF_Training_3-afterica-raw.fif","24":"raw_ica\/ZYF_Training_4-afterica-raw.fif","25":"raw_ica\/ZYF_Training_5-afterica-raw.fif"}}